{"_id":"ba046a62696084a30b4bec2d569f57d4","formattedAddress":"地址待补充","imageUrl":"cloud://your-env-id/placeholder.jpg","location":{"coordinates":[121.47,31.23],"type":"Point"},"status":"pending","address":"地址待补充","aiSolution":"示例AI建议","createTime":{"$date":"2026-01-09T04:31:31.314Z"},"_openid":"oOJhu3QmRKlk8Iuu87G6ol0IrDyQ"}
{"_id":"8656c024696085200b46223a78c5acbb","location":{"coordinates":[121.47,31.23],"type":"Point"},"status":"pending","address":"地址待补充","aiSolution":"示例AI建议","createTime":{"$date":"2026-01-09T04:33:36.445Z"},"formattedAddress":"地址待补充","imageUrl":"cloud://your-env-id/placeholder.jpg","_openid":"oOJhu3QmRKlk8Iuu87G6ol0IrDyQ"}
{"_id":"22be1a4269609c2f0b43a6761e495385","createTime":{"$date":"2026-01-09T06:11:59.214Z"},"formattedAddress":"荣盛花语书苑(经贸街)","imageUrl":"cloud://cloud1-8g7mscenc95268ca.636c-cloud1-8g7mscenc95268ca-1394834869/issues/1767939117718-710.jpg","location":{"coordinates":[112.97603814019097,28.158570692274306],"type":"Point"},"status":"pending","_openid":"oOJhu3QmRKlk8Iuu87G6ol0IrDyQ","address":"湖南省长沙市天心区书院南路577号","aiSolution":"检测到台阶缺失坡道，建议增设 1:12 无障碍坡道，预算约 500 元。"}
{"_id":"8656c02469609e590b49215300fc8a27","aiSolution":"检测到台阶缺失坡道，建议增设 1:12 无障碍坡道，预算约 500 元。","imageUrl":"cloud://cloud1-8g7mscenc95268ca.636c-cloud1-8g7mscenc95268ca-1394834869/issues/1767939672004-821.jpg","_openid":"oOJhu3QmRKlk8Iuu87G6ol0IrDyQ","address":"定位成功","createTime":{"$date":"2026-01-09T06:21:13.125Z"},"formattedAddress":"定位成功","images":["cloud://cloud1-8g7mscenc95268ca.636c-cloud1-8g7mscenc95268ca-1394834869/issues/1767939672004-821.jpg"],"location":{"type":"Point","coordinates":[112.97614366319445,28.158627115885416]},"status":"pending"}
{"_id":"7f4b671369609ea70b46fd2954426ec7","imageUrl":"cloud://cloud1-8g7mscenc95268ca.636c-cloud1-8g7mscenc95268ca-1394834869/issues/1767939750778-322.jpg","images":["cloud://cloud1-8g7mscenc95268ca.636c-cloud1-8g7mscenc95268ca-1394834869/issues/1767939750778-322.jpg","cloud://cloud1-8g7mscenc95268ca.636c-cloud1-8g7mscenc95268ca-1394834869/issues/1767939750778-269.jpg","cloud://cloud1-8g7mscenc95268ca.636c-cloud1-8g7mscenc95268ca-1394834869/issues/1767939750779-489.jpg"],"location":{"coordinates":[112.97614366319445,28.158627115885416],"type":"Point"},"address":"定位成功","formattedAddress":"定位成功","status":"pending","_openid":"oOJhu3QmRKlk8Iuu87G6ol0IrDyQ","aiSolution":"检测到台阶缺失坡道，建议增设 1:12 无障碍坡道，预算约 500 元。","createTime":{"$date":"2026-01-09T06:22:31.858Z"}}
{"_id":"7f4b67136960a3ac0b479cea7e3327fc","_openid":"oOJhu3QmRKlk8Iuu87G6ol0IrDyQ","formattedAddress":"定位成功","images":["cloud://cloud1-8g7mscenc95268ca.636c-cloud1-8g7mscenc95268ca-1394834869/issues/1767941035364-274.jpg"],"location":{"coordinates":[112.97618353949653,28.158581000434026],"type":"Point"},"address":"定位成功","aiSolution":"检测到台阶缺失坡道，建议增设 1:12 无障碍坡道，预算约 500 元。","createTime":{"$date":"2026-01-09T06:43:56.515Z"},"imageUrl":"cloud://cloud1-8g7mscenc95268ca.636c-cloud1-8g7mscenc95268ca-1394834869/issues/1767941035364-274.jpg","status":"pending"}
{"_id":"cc84495d6961d9200b650f2e3ec5607d","location":{"coordinates":[112.97616373697916,28.158581000434026],"type":"Point"},"_openid":"oOJhu3QmRKlk8Iuu87G6ol0IrDyQ","description":"。。。。。。。。。","imageUrl":"cloud://cloud1-8g7mscenc95268ca.636c-cloud1-8g7mscenc95268ca-1394834869/issues/1768020256218-0.jpg","status":"pending","address":"定位成功","aiSolution":"检测到路面坑洼不平，建议进行修复并确保路面平整。","createTime":{"$date":"2026-01-10T04:44:16.934Z"},"formattedAddress":"定位成功","images":["cloud://cloud1-8g7mscenc95268ca.636c-cloud1-8g7mscenc95268ca-1394834869/issues/1768020256218-0.jpg"]}
{"_id":"ab9277866961dc210b7181512b386a2e","images":["cloud://cloud1-8g7mscenc95268ca.636c-cloud1-8g7mscenc95268ca-1394834869/issues/1768021025041-0.jpg"],"location":{"coordinates":[112.97617,28.158623],"type":"Point"},"address":"湖南省长沙市天心区经贸街","createTime":{"$date":"2026-01-10T04:57:05.76Z"},"formattedAddress":"湖南省长沙市天心区经贸街","status":"pending","_openid":"oOJhu3QmRKlk8Iuu87G6ol0IrDyQ","aiSolution":"检测到公共厕所未设置无障碍设施，建议增设无障碍卫生间。","description":"。。。。。。。。。","imageUrl":"cloud://cloud1-8g7mscenc95268ca.636c-cloud1-8g7mscenc95268ca-1394834869/issues/1768021025041-0.jpg"}
{"_id":"da8988ea6961dc650b6a82015f32b099","description":"1111111","formattedAddress":"定位成功","imageUrl":"cloud://cloud1-8g7mscenc95268ca.636c-cloud1-8g7mscenc95268ca-1394834869/issues/1768021092698-0.jpg","location":{"coordinates":[112.97616563585069,28.158578016493056],"type":"Point"},"status":"pending","_openid":"oOJhu3QmRKlk8Iuu87G6ol0IrDyQ","aiSolution":"检测到盲道被占用，建议清理障碍物并设置警示标识。","createTime":{"$date":"2026-01-10T04:58:13.456Z"},"images":["cloud://cloud1-8g7mscenc95268ca.636c-cloud1-8g7mscenc95268ca-1394834869/issues/1768021092698-0.jpg"],"address":"定位成功"}
{"_id":"a23524646961dcec0b6b3a8060378178","formattedAddress":"湖南省长沙市天心区沙湖街128号","location":{"coordinates":[112.97634,28.160343],"type":"Point"},"status":"pending","address":"湖南省长沙市天心区沙湖街128号","imageUrl":"cloud://cloud1-8g7mscenc95268ca.636c-cloud1-8g7mscenc95268ca-1394834869/issues/1768021227828-0.jpg","images":["cloud://cloud1-8g7mscenc95268ca.636c-cloud1-8g7mscenc95268ca-1394834869/issues/1768021227828-0.jpg"],"_openid":"oOJhu3QmRKlk8Iuu87G6ol0IrDyQ","aiSolution":"检测到盲道被占用，建议清理障碍物并设置警示标识。","createTime":{"$date":"2026-01-10T05:00:28.527Z"},"description":"。。。。。。。"}
{"_id":"def9fa846961e11d0b65fb6657cd7a1e","aiSolution":"检测到楼梯缺失扶手，建议安装不锈钢扶手。","createTime":{"$date":"2026-01-10T05:18:21.546Z"},"formattedAddress":"定位成功","imageUrl":"cloud://cloud1-8g7mscenc95268ca.636c-cloud1-8g7mscenc95268ca-1394834869/issues/1768022300822-0.jpg","location":{"coordinates":[112.9763560655382,28.15858859592014],"type":"Point"},"description":"。。。。。。","images":["cloud://cloud1-8g7mscenc95268ca.636c-cloud1-8g7mscenc95268ca-1394834869/issues/1768022300822-0.jpg"],"status":"pending","_openid":"oOJhu3QmRKlk8Iuu87G6ol0IrDyQ","address":"定位成功"}
{"_id":"8f6c3a636961ef4b0b78fd17570c3dca","status":"pending","aiSolution":"检测到路面坑洼不平，建议进行修复并确保路面平整。","createTime":{"$date":"2026-01-10T06:18:51.674Z"},"description":"。。。。。","location":{"coordinates":[112.979164,28.152021],"type":"Point"},"_openid":"oOJhu3QmRKlk8Iuu87G6ol0IrDyQ","address":"湖南省长沙市天心区赤岭路街道赤岭路与新建西路交汇处万润时光里","formattedAddress":"湖南省长沙市天心区赤岭路街道赤岭路与新建西路交汇处万润时光里","imageUrl":"cloud://cloud1-8g7mscenc95268ca.636c-cloud1-8g7mscenc95268ca-1394834869/issues/1768025930680-0.jpg","images":["cloud://cloud1-8g7mscenc95268ca.636c-cloud1-8g7mscenc95268ca-1394834869/issues/1768025930680-0.jpg"]}
{"_id":"b4498fc8696227d70b784c09365f3b4b","_openid":"oOJhu3QmRKlk8Iuu87G6ol0IrDyQ","address":"湖南省长沙市天心区书院南路577号","aiSolution":"检测到楼梯缺失扶手，建议安装不锈钢扶手。","createTime":{"$date":"2026-01-10T10:20:07.033Z"},"imageUrl":"cloud://cloud1-8g7mscenc95268ca.636c-cloud1-8g7mscenc95268ca-1394834869/issues/1768040406312-0.jpg","status":"pending","description":"。。。。。。。","formattedAddress":"湖南省长沙市天心区书院南路577号","images":["cloud://cloud1-8g7mscenc95268ca.636c-cloud1-8g7mscenc95268ca-1394834869/issues/1768040406312-0.jpg"],"location":{"coordinates":[112.9762,28.158583],"type":"Point"}}
{"_id":"d84694f2696317730b92be9823748ebc","location":{"coordinates":[112.97619,28.158587],"type":"Point"},"status":"pending","_openid":"oOJhu3QmRKlk8Iuu87G6ol0IrDyQ","address":"湖南省长沙市天心区书院南路577号","description":"是假的假的假的就是假的假的假的","imageUrl":"cloud://cloud1-8g7mscenc95268ca.636c-cloud1-8g7mscenc95268ca-1394834869/issues/1768101746330-0.jpg","userSuggestion":"手机电不多的肯定九点半","aiSolution":"检测到台阶缺失坡道，建议增设 1:12 无障碍坡道，预算约 500 元。","createTime":{"$date":"2026-01-11T03:22:27.066Z"},"formattedAddress":"湖南省长沙市天心区书院南路577号","images":["cloud://cloud1-8g7mscenc95268ca.636c-cloud1-8g7mscenc95268ca-1394834869/issues/1768101746330-0.jpg"]}
{"_id":"47985914696327570b87fbaa540c1477","createTime":{"$date":"2026-01-11T04:30:15.282Z"},"formattedAddress":"湖南省长沙市天心区经贸街","imageUrl":"cloud://cloud1-8g7mscenc95268ca.636c-cloud1-8g7mscenc95268ca-1394834869/issues/1768105814592-0.jpg","location":{"coordinates":[112.976036,28.158772],"type":"Point"},"_openid":"oOJhu3QmRKlk8Iuu87G6ol0IrDyQ","description":"司机电话四十你都觉得姐姐","images":["cloud://cloud1-8g7mscenc95268ca.636c-cloud1-8g7mscenc95268ca-1394834869/issues/1768105814592-0.jpg"],"status":"pending","userSuggestion":"丹尼斯都不想就是难受","address":"湖南省长沙市天心区经贸街","aiSolution":"检测到台阶缺失坡道，建议增设 1:12 无障碍坡道，预算约 500 元。"}
{"_id":"47985914696327b70b87ff671b455e30","userSuggestion":"绿豆的哈基米","_openid":"oOJhu3QmRKlk8Iuu87G6ol0IrDyQ","address":"湖南省长沙市天心区金盆岭街道南湖路沙湖街128号","createTime":{"$date":"2026-01-11T04:31:51.921Z"},"formattedAddress":"湖南省长沙市天心区金盆岭街道南湖路沙湖街128号","imageUrl":"cloud://cloud1-8g7mscenc95268ca.636c-cloud1-8g7mscenc95268ca-1394834869/issues/1768105911225-0.jpg","images":["cloud://cloud1-8g7mscenc95268ca.636c-cloud1-8g7mscenc95268ca-1394834869/issues/1768105911225-0.jpg"],"status":"pending","aiSolution":"检测到盲道被占用，建议清理障碍物并设置警示标识。","description":"哈基米南北绿豆","location":{"coordinates":[112.97702,28.158957],"type":"Point"}}
{"_id":"cd349d8f696329af0b902c517ed2be31","address":"湖南省长沙市天心区书院南路577号","createTime":{"$date":"2026-01-11T04:40:15.407Z"},"description":"上帝视角的还是看手机的基督教党建","formattedAddress":"湖南省长沙市天心区书院南路577号","imageUrl":"cloud://cloud1-8g7mscenc95268ca.636c-cloud1-8g7mscenc95268ca-1394834869/issues/1768106414362-0.jpg","status":"pending","userSuggestion":"哈基米希望明天能到吗还是啥的都没有了吗你","_openid":"oOJhu3QmRKlk8Iuu87G6ol0IrDyQ","aiSolution":"检测到路面坑洼不平，建议进行修复并确保路面平整。","images":["cloud://cloud1-8g7mscenc95268ca.636c-cloud1-8g7mscenc95268ca-1394834869/issues/1768106414362-0.jpg"],"location":{"type":"Point","coordinates":[112.97619,28.158587]}}
{"_id":"22be1a4269632d450b8bd03571bc7149","formattedAddress":"湖南省长沙市天心区书院南路577号","imageUrl":"cloud://cloud1-8g7mscenc95268ca.636c-cloud1-8g7mscenc95268ca-1394834869/issues/1768107332714-0.jpg","location":{"coordinates":[112.97618,28.158596],"type":"Point"},"aiSolution":"检测到盲道被占用，建议清理障碍物并设置警示标识。","createTime":{"$date":"2026-01-11T04:55:33.389Z"},"images":["cloud://cloud1-8g7mscenc95268ca.636c-cloud1-8g7mscenc95268ca-1394834869/issues/1768107332714-0.jpg"],"status":"pending","userSuggestion":"电脑都电脑错了错了错快点快点","_openid":"oOJhu3QmRKlk8Iuu87G6ol0IrDyQ","address":"湖南省长沙市天心区书院南路577号","description":"自己看妇科都不送世界等级低手机上你的课"}
{"_id":"b4498fc8696331550b9275910063c10a","_openid":"oOJhu3QmRKlk8Iuu87G6ol0IrDyQ","formattedAddress":"湖南省长沙市天心区书院南路577号","imageUrl":"cloud://cloud1-8g7mscenc95268ca.636c-cloud1-8g7mscenc95268ca-1394834869/issues/1768108372471-0.jpg","userSuggestion":"基地的考试背带裤佛法你发了分开发你发你","address":"湖南省长沙市天心区书院南路577号","aiSolution":"检测到公共厕所未设置无障碍设施，建议增设无障碍卫生间。","createTime":{"$date":"2026-01-11T05:12:53.227Z"},"description":"哈基米降低带你兜风减肥咖啡看","images":["cloud://cloud1-8g7mscenc95268ca.636c-cloud1-8g7mscenc95268ca-1394834869/issues/1768108372471-0.jpg"],"location":{"type":"Point","coordinates":[112.976204,28.158587]},"status":"pending"}
{"_id":"74337284696333eb0b93416c2395ec72","location":{"coordinates":[112.97629,28.15859],"type":"Point"},"status":"pending","address":"湖南省长沙市天心区书院南路577号","aiSolution":"检测到楼梯缺失扶手，建议安装不锈钢扶手。","createTime":{"$date":"2026-01-11T05:23:55.723Z"},"description":"说你是肯德基都不上课睡你的觉","formattedAddress":"湖南省长沙市天心区书院南路577号","images":["cloud://cloud1-8g7mscenc95268ca.636c-cloud1-8g7mscenc95268ca-1394834869/issues/1768109034996-0.jpg"],"userSuggestion":"这是一个建议","_openid":"oOJhu3QmRKlk8Iuu87G6ol0IrDyQ","imageUrl":"cloud://cloud1-8g7mscenc95268ca.636c-cloud1-8g7mscenc95268ca-1394834869/issues/1768109034996-0.jpg"}
{"_id":"22be1a42696335a30b8c7cac197494a6","address":"定位成功","aiSolution":"检测到公共厕所未设置无障碍设施，建议增设无障碍卫生间。","formattedAddress":"定位成功","imageUrl":"cloud://cloud1-8g7mscenc95268ca.636c-cloud1-8g7mscenc95268ca-1394834869/issues/1768109474582-0.jpg","images":["cloud://cloud1-8g7mscenc95268ca.636c-cloud1-8g7mscenc95268ca-1394834869/issues/1768109474582-0.jpg"],"location":{"type":"Point","coordinates":[112.97616563585069,28.158581000434026]},"userSuggestion":"user苏哥跳哪","_openid":"oOJhu3QmRKlk8Iuu87G6ol0IrDyQ","createTime":{"$date":"2026-01-11T05:31:15.253Z"},"description":"注意了这是一条","status":"pending"}
{"_id":"47985914696336750b895eb023f26634","status":"pending","_openid":"oOJhu3QmRKlk8Iuu87G6ol0IrDyQ","aiSolution":"检测到路面坑洼不平，建议进行修复并确保路面平整。","formattedAddress":"湖南省长沙市天心区书院南路577号","location":{"coordinates":[112.97618,28.158596],"type":"Point"},"userSuggestion":"这是一条最新的建议","address":"湖南省长沙市天心区书院南路577号","createTime":{"$date":"2026-01-11T05:34:45.164Z"},"description":"这是一条最新的数据","imageUrl":"cloud://cloud1-8g7mscenc95268ca.636c-cloud1-8g7mscenc95268ca-1394834869/issues/1768109684428-0.jpg","images":["cloud://cloud1-8g7mscenc95268ca.636c-cloud1-8g7mscenc95268ca-1394834869/issues/1768109684428-0.jpg"]}
{"_id":"4289fa8169633a7f0b9399ba19e794ee","status":"pending","address":"湖南省长沙市天心区书院南路577号","createTime":{"$date":"2026-01-11T05:51:59.334Z"},"formattedAddress":"湖南省长沙市天心区书院南路577号","imageUrl":"cloud://cloud1-8g7mscenc95268ca.636c-cloud1-8g7mscenc95268ca-1394834869/issues/1768110718543-0.jpg","images":["cloud://cloud1-8g7mscenc95268ca.636c-cloud1-8g7mscenc95268ca-1394834869/issues/1768110718543-0.jpg"],"userSuggestion":"俺弟办法疯狂不想继续偶像活动看似视而不见外地工业学院爹看不到你知豆不？？？","_openid":"oOJhu3QmRKlk8Iuu87G6ol0IrDyQ","aiSolution":"检测到路面坑洼不平，建议进行修复并确保路面平整。","description":"手机懂得送到家你发了发酒疯哈佛反目成仇康复科佛法客服减肥减肥客服呢都没打开打你打你打你","location":{"coordinates":[112.97624,28.158607],"type":"Point"}}
{"_id":"7433728469633b040b93ef971dd0db2e","formattedAddress":"湖南省长沙市天心区书院南路577号","status":"pending","userSuggestion":"降低点别的咳嗽声大家都","aiSolution":"检测到台阶缺失坡道，建议增设 1:12 无障碍坡道，预算约 500 元。","imageUrl":"cloud://cloud1-8g7mscenc95268ca.636c-cloud1-8g7mscenc95268ca-1394834869/issues/1768110851632-0.jpg","images":["cloud://cloud1-8g7mscenc95268ca.636c-cloud1-8g7mscenc95268ca-1394834869/issues/1768110851632-0.jpg"],"location":{"coordinates":[112.97611,28.158587],"type":"Point"},"_openid":"oOJhu3QmRKlk8Iuu87G6ol0IrDyQ","address":"湖南省长沙市天心区书院南路577号","createTime":{"$date":"2026-01-11T05:54:12.384Z"},"description":"最新活动的还是死地"}
{"_id":"dab5292a69633e290b9660337f3747e9","userSuggestion":"脑子什么发布的咳嗽上班打卡打卡打卡","_openid":"oOJhu3QmRKlk8Iuu87G6ol0IrDyQ","createTime":{"$date":"2026-01-11T06:07:37.194Z"},"description":"这是一个最新的数据","imageUrl":"cloud://cloud1-8g7mscenc95268ca.636c-cloud1-8g7mscenc95268ca-1394834869/issues/1768111656373-0.jpg","status":"pending","address":"湖南省长沙市天心区书院南路577号","aiSolution":"检测到路面坑洼不平，建议进行修复并确保路面平整。","formattedAddress":"湖南省长沙市天心区书院南路577号","images":["cloud://cloud1-8g7mscenc95268ca.636c-cloud1-8g7mscenc95268ca-1394834869/issues/1768111656373-0.jpg"],"location":{"coordinates":[112.9762,28.158592],"type":"Point"}}
{"_id":"4289fa8169634d380b95eb8e4cec591a","location":{"coordinates":[112.97621,28.158575],"type":"Point"},"userSuggestion":"基督教党建放不放假行动几点到家","_openid":"oOJhu3QmRKlk8Iuu87G6ol0IrDyQ","aiSolution":"检测到楼梯缺失扶手，建议安装不锈钢扶手。","description":"等级低的经典诵读尽快发佛法见佛覅分开","formattedAddress":"湖南省长沙市天心区书院南路577号","imageUrl":"cloud://cloud1-8g7mscenc95268ca.636c-cloud1-8g7mscenc95268ca-1394834869/issues/1768115511544-0.jpg","status":"pending","address":"湖南省长沙市天心区书院南路577号","createTime":{"$date":"2026-01-11T07:11:52.25Z"},"images":["cloud://cloud1-8g7mscenc95268ca.636c-cloud1-8g7mscenc95268ca-1394834869/issues/1768115511544-0.jpg"]}
{"_id":"8e2c0a2f69634e6e0b98a14c428f4e37","images":["cloud://cloud1-8g7mscenc95268ca.636c-cloud1-8g7mscenc95268ca-1394834869/issues/1768115821305-0.jpg"],"location":{"coordinates":[112.97621,28.158575],"type":"Point"},"status":"pending","address":"湖南省长沙市天心区书院南路577号","aiSolution":"检测到楼梯缺失扶手，建议安装不锈钢扶手。","imageUrl":"cloud://cloud1-8g7mscenc95268ca.636c-cloud1-8g7mscenc95268ca-1394834869/issues/1768115821305-0.jpg","userSuggestion":"哈哈哈嗝嗝嗝发发发v记四级","_openid":"oOJhu3QmRKlk8Iuu87G6ol0IrDyQ","createTime":{"$date":"2026-01-11T07:17:02.108Z"},"description":"韩国进口快快快快快快快","formattedAddress":"湖南省长沙市天心区书院南路577号"}
{"_id":"ba046a62696350950b9c3fdc38c524d4","images":["cloud://cloud1-8g7mscenc95268ca.636c-cloud1-8g7mscenc95268ca-1394834869/issues/1768116373233-0.jpg"],"userSuggestion":"你走到哪上课伤心哦是你是你搜索就是","_openid":"oOJhu3QmRKlk8Iuu87G6ol0IrDyQ","createTime":{"$date":"2026-01-11T07:26:13.922Z"},"description":"是的呢到底几点看到你的就","formattedAddress":"湖南省长沙市天心区书院南路577号","imageUrl":"cloud://cloud1-8g7mscenc95268ca.636c-cloud1-8g7mscenc95268ca-1394834869/issues/1768116373233-0.jpg","location":{"coordinates":[112.97613,28.158634],"type":"Point"},"status":"pending","address":"湖南省长沙市天心区书院南路577号","aiSolution":"检测到盲道被占用，建议清理障碍物并设置警示标识。"}
{"_id":"4289fa816963509d0b963ae16a83c303","location":{"coordinates":[112.97613,28.158634],"type":"Point"},"address":"湖南省长沙市天心区书院南路577号","createTime":{"$date":"2026-01-11T07:26:21.901Z"},"description":"是的呢到底几点看到你的就","formattedAddress":"湖南省长沙市天心区书院南路577号","status":"pending","userSuggestion":"你走到哪上课伤心哦是你是你搜索就是","_openid":"oOJhu3QmRKlk8Iuu87G6ol0IrDyQ","aiSolution":"检测到盲道被占用，建议清理障碍物并设置警示标识。","imageUrl":"cloud://cloud1-8g7mscenc95268ca.636c-cloud1-8g7mscenc95268ca-1394834869/issues/1768116381274-0.jpg","images":["cloud://cloud1-8g7mscenc95268ca.636c-cloud1-8g7mscenc95268ca-1394834869/issues/1768116381274-0.jpg"]}
{"_id":"cd349d8f696350d30b947ccd14c126c7","_openid":"oOJhu3QmRKlk8Iuu87G6ol0IrDyQ","createTime":{"$date":"2026-01-11T07:27:15.579Z"},"description":"。。。。。。。。。。。","formattedAddress":"定位成功","status":"pending","address":"定位成功","aiSolution":"检测到台阶缺失坡道，建议增设 1:12 无障碍坡道，预算约 500 元。","imageUrl":"cloud://cloud1-8g7mscenc95268ca.636c-cloud1-8g7mscenc95268ca-1394834869/issues/1768116434870-0.jpg","images":["cloud://cloud1-8g7mscenc95268ca.636c-cloud1-8g7mscenc95268ca-1394834869/issues/1768116434870-0.jpg"],"location":{"coordinates":[112.97619954427083,28.158588053385415],"type":"Point"},"userSuggestion":"还是四百多四十一是不是不当回事"}
{"_id":"7f4b6713696351290b93ab0775e43bdc","location":{"coordinates":[112.976204,28.158588],"type":"Point"},"userSuggestion":"小啊好的你都但是是你是本地星光都市好的好的","address":"湖南省长沙市天心区书院南路577号","createTime":{"$date":"2026-01-11T07:28:41.03Z"},"description":"拿东西漱口水别的快递就是就是","formattedAddress":"湖南省长沙市天心区书院南路577号","imageUrl":"cloud://cloud1-8g7mscenc95268ca.636c-cloud1-8g7mscenc95268ca-1394834869/issues/1768116520293-0.jpg","images":["cloud://cloud1-8g7mscenc95268ca.636c-cloud1-8g7mscenc95268ca-1394834869/issues/1768116520293-0.jpg"],"status":"pending","_openid":"oOJhu3QmRKlk8Iuu87G6ol0IrDyQ","aiSolution":"检测到公共厕所未设置无障碍设施，建议增设无障碍卫生间。"}
{"_id":"4289fa81696353f10b969c52157e055f","_openid":"oOJhu3QmRKlk8Iuu87G6ol0IrDyQ","formattedAddress":"湖南省长沙市天心区书院南路577号","images":["cloud://cloud1-8g7mscenc95268ca.636c-cloud1-8g7mscenc95268ca-1394834869/issues/1768117232395-0.jpg"],"location":{"coordinates":[112.9762,28.158583],"type":"Point"},"status":"pending","userSuggestion":"黄家驹反弹豪华版","address":"湖南省长沙市天心区书院南路577号","aiSolution":"检测到台阶缺失坡道，建议增设 1:12 无障碍坡道，预算约 500 元。","createTime":{"$date":"2026-01-11T07:40:33.242Z"},"description":"。你经常就顾提出就公交卡不尴尬","imageUrl":"cloud://cloud1-8g7mscenc95268ca.636c-cloud1-8g7mscenc95268ca-1394834869/issues/1768117232395-0.jpg"}
{"_id":"ab927786696354d40b989713222fcd3d","description":"自己是你的快手极速版什么地多喝开水四百多你弟弟好的一点也好","images":["cloud://cloud1-8g7mscenc95268ca.636c-cloud1-8g7mscenc95268ca-1394834869/issues/1768117459985-0.jpg"],"location":{"coordinates":[112.9762,28.158583],"type":"Point"},"status":"pending","userSuggestion":"第四我不是不小心咳嗽哈骄傲的家附近佛的就是不想你","address":"湖南省长沙市天心区书院南路577号","aiSolution":"检测到公共厕所未设置无障碍设施，建议增设无障碍卫生间。","formattedAddress":"湖南省长沙市天心区书院南路577号","imageUrl":"cloud://cloud1-8g7mscenc95268ca.636c-cloud1-8g7mscenc95268ca-1394834869/issues/1768117459985-0.jpg","_openid":"oOJhu3QmRKlk8Iuu87G6ol0IrDyQ","createTime":{"$date":"2026-01-11T07:44:20.71Z"}}
{"_id":"def9fa84696355b50b8c5995629abe68","createTime":{"$date":"2026-01-11T07:48:05.115Z"},"description":"意思是你说的弄的等你等你","imageUrl":"cloud://cloud1-8g7mscenc95268ca.636c-cloud1-8g7mscenc95268ca-1394834869/issues/1768117684390-0.jpg","images":["cloud://cloud1-8g7mscenc95268ca.636c-cloud1-8g7mscenc95268ca-1394834869/issues/1768117684390-0.jpg"],"location":{"type":"Point","coordinates":[112.97621,28.158583]},"userSuggestion":"新疆送手机手机靖西县觉醒年代手机卡","aiSolution":"检测到公共厕所未设置无障碍设施，建议增设无障碍卫生间。","formattedAddress":"湖南省长沙市天心区书院南路577号","status":"pending","_openid":"oOJhu3QmRKlk8Iuu87G6ol0IrDyQ","address":"湖南省长沙市天心区书院南路577号"}
